mcp_x_post/__init__.py
mcp_x_post/server.py
mcp_x_post-0.1.1.dist-info/METADATA
mcp_x_post-0.1.1.dist-info/WHEEL
mcp_x_post-0.1.1.dist-info/entry_points.txt
mcp_x_post-0.1.1.dist-info/RECORD
