Metadata-Version: 2.4
Name: mcp-x-post
Version: 0.1.1
Summary: A MCP server project for posting tweet on X
Author-email: ushishu <shuzo.1128@gmail.com>
Requires-Python: >=3.12.5
Requires-Dist: httpx>=0.28.1
Requires-Dist: mcp>=1.2.1
Requires-Dist: python-dotenv>=1.0.1
Requires-Dist: tweepy>=4.15.0
